mcp_pokemon_server_cstest/__init__.py
mcp_pokemon_server_cstest/zekang.py
mcp_pokemon_server_cstest-4.9.0.dist-info/METADATA
mcp_pokemon_server_cstest-4.9.0.dist-info/WHEEL
mcp_pokemon_server_cstest-4.9.0.dist-info/entry_points.txt
mcp_pokemon_server_cstest-4.9.0.dist-info/RECORD
