Metadata-Version: 2.4
Name: mcp-pokemon-server-cstest
Version: 4.9.0
Summary: Add your description here
Requires-Python: >=3.10
Requires-Dist: mcp[cli]>=1.6.0
